sphinxview/ext.py
sphinxview/sphinxview.js
sphinxview/sphinxview.py
sphinxview/__init__.py
sphinxview-0.2.0.dist-info/DESCRIPTION.rst
sphinxview-0.2.0.dist-info/entry_points.txt
sphinxview-0.2.0.dist-info/METADATA
sphinxview-0.2.0.dist-info/metadata.json
sphinxview-0.2.0.dist-info/RECORD
sphinxview-0.2.0.dist-info/top_level.txt
sphinxview-0.2.0.dist-info/WHEEL
