Metadata-Version: 2.0
Name: sphinxview
Version: 0.2.0
Summary: Serves your Sphinx project and reloads pages on source changes
Home-page: https://github.com/trarbr/sphinxview
Author: Troels Brødsgaard
Author-email: tr@arbr.dk
License: BSD
Requires-Dist: sphinx
Requires-Dist: docopt
